{
    "bronze": {
        "dagger": {
            "image": "assets/itemsImages/weapons/bronze/dagger/bronze-dagger",
            "damage": 1,
            "value": 1,
            "speed": 0.5
        },
        "sword": {
            "image": "assets/itemsImages/weapons/bronze/sword/bronze-sword",
            "damage": 2,
            "value": 2,
            "speed": 0.7
        },
        "axe": {
            "image": "assets/itemsImages/weapons/bronze/axe/bronze-axe",
            "damage": 5,
            "value": 3,
            "speed": 1.3
        }
    },
    "steel": {
        "dagger": {
            "image": "assets/itemsImages/weapons/steel/dagger/steel-dagger",
            "damage": 2,
            "value": 2,
            "speed": 0.5
        },
        "sword": {
            "image": "assets/itemsImages/weapons/steel/sword/steel-sword",
            "damage": 4,
            "value": 4,
            "speed": 0.7
        },
        "axe": {
            "image": "assets/itemsImages/weapons/steel/axe/steel-axe",
            "damage": 6,
            "value": 5,
            "speed": 1.3
        }
    },
    "diamond": {
        "dagger": {
            "image": "assets/itemsImages/weapons/diamond/dagger/diamond-dagger",
            "damage": 3,
            "value": 4,
            "speed": 0.5
        },
        "sword": {
            "image": "assets/itemsImages/weapons/diamond/sword/diamond-sword",
            "damage": 6,
            "value": 6,
            "speed": 0.7
        },
        "axe": {
            "image": "assets/itemsImages/weapons/diamond/axe/diamond-axe",
            "damage": 9,
            "value": 7,
            "speed": 1.3
        }
    }
}